anchovy_css/__init__.py
anchovy_css/__main__.py
anchovy_css/cli.py
anchovy_css/parser.py
anchovy_css-0.1.1.dist-info/LICENSE
anchovy_css-0.1.1.dist-info/METADATA
anchovy_css-0.1.1.dist-info/WHEEL
anchovy_css-0.1.1.dist-info/entry_points.txt
anchovy_css-0.1.1.dist-info/top_level.txt
anchovy_css-0.1.1.dist-info/RECORD
