Metadata-Version: 2.1
Name: anchovy-css
Version: 0.1.1
Summary: A simple, pure-Python CSS pre-processor.
Author-email: Daniel Foerster <pydsigner@gmail.com>
License: Apache-2.0
Project-URL: Source, https://github.com/pydsigner/anchovy_css
Keywords: css
Classifier: Development Status :: 3 - Alpha
Classifier: Intended Audience :: Developers
Classifier: License :: OSI Approved :: Apache Software License
Classifier: Operating System :: OS Independent
Classifier: Programming Language :: Python :: 3
Classifier: Programming Language :: Python :: 3 :: Only
Classifier: Programming Language :: Python :: 3.10
Classifier: Programming Language :: Python :: 3.11
Classifier: Topic :: Internet :: WWW/HTTP
Classifier: Topic :: Software Development :: Pre-processors
Classifier: Topic :: Text Processing :: Markup
Classifier: Typing :: Typed
Requires-Python: >=3.10
License-File: LICENSE
Requires-Dist: tinycss2 >=1.1.1
Provides-Extra: cq
Requires-Dist: anchovy-css[format] ; extra == 'cq'
Requires-Dist: pylint ; extra == 'cq'
Requires-Dist: pyright ; extra == 'cq'
Requires-Dist: pytest ; extra == 'cq'
Requires-Dist: pytest-cov ; extra == 'cq'
Provides-Extra: format
Requires-Dist: lightningcss >=0.1.1 ; extra == 'format'
